{
  "$schema": "https://developer.microsoft.com/json-schemas/fabric/item/ontology/entityType/1.0.0/schema.json",
  "id": "227962527593450",
  "namespace": "usertypes",
  "baseEntityTypeId": null,
  "name": "fact_financial_transactions",
  "entityIdParts": [
    "7220000870019023057"
  ],
  "displayNamePropertyId": null,
  "namespaceType": "Imported",
  "visibility": "Visible",
  "properties": [
    {
      "id": "7220000870019023057",
      "name": "transaction_key",
      "redefines": null,
      "baseTypeNamespaceType": null,
      "valueType": "BigInt"
    },
    {
      "id": "7220000843981076723",
      "name": "student_key",
      "redefines": null,
      "baseTypeNamespaceType": null,
      "valueType": "BigInt"
    },
    {
      "id": "7220000820911932253",
      "name": "fee_type_key",
      "redefines": null,
      "baseTypeNamespaceType": null,
      "valueType": "BigInt"
    },
    {
      "id": "7220000800665327898",
      "name": "academic_period_key",
      "redefines": null,
      "baseTypeNamespaceType": null,
      "valueType": "BigInt"
    },
    {
      "id": "7220000778064424471",
      "name": "course_key",
      "redefines": null,
      "baseTypeNamespaceType": null,
      "valueType": "BigInt"
    },
    {
      "id": "7220000750900443681",
      "name": "transaction_date_key",
      "redefines": null,
      "baseTypeNamespaceType": null,
      "valueType": "BigInt"
    },
    {
      "id": "7220000731701151882",
      "name": "due_date_key",
      "redefines": null,
      "baseTypeNamespaceType": null,
      "valueType": "BigInt"
    },
    {
      "id": "7220000709750495468",
      "name": "transaction_id",
      "redefines": null,
      "baseTypeNamespaceType": null,
      "valueType": "String"
    },
    {
      "id": "7220000689418538828",
      "name": "transaction_type",
      "redefines": null,
      "baseTypeNamespaceType": null,
      "valueType": "String"
    },
    {
      "id": "7220000668464242710",
      "name": "amount",
      "redefines": null,
      "baseTypeNamespaceType": null,
      "valueType": "Double"
    },
    {
      "id": "7220000644719048969",
      "name": "signed_amount",
      "redefines": null,
      "baseTypeNamespaceType": null,
      "valueType": "Double"
    },
    {
      "id": "7220000620411651923",
      "name": "currency",
      "redefines": null,
      "baseTypeNamespaceType": null,
      "valueType": "String"
    },
    {
      "id": "7220000596613127316",
      "name": "payment_method",
      "redefines": null,
      "baseTypeNamespaceType": null,
      "valueType": "String"
    },
    {
      "id": "7220000577198543422",
      "name": "reference_number",
      "redefines": null,
      "baseTypeNamespaceType": null,
      "valueType": "String"
    },
    {
      "id": "7220000556372312437",
      "name": "is_overdue",
      "redefines": null,
      "baseTypeNamespaceType": null,
      "valueType": "Boolean"
    },
    {
      "id": "7220000532304006856",
      "name": "days_overdue",
      "redefines": null,
      "baseTypeNamespaceType": null,
      "valueType": "BigInt"
    },
    {
      "id": "7220000514497427343",
      "name": "outstanding_balance_after",
      "redefines": null,
      "baseTypeNamespaceType": null,
      "valueType": "Double"
    },
    {
      "id": "7220000488399061983",
      "name": "Total_Revenue",
      "redefines": null,
      "baseTypeNamespaceType": null,
      "valueType": "Double"
    },
    {
      "id": "7220000442330261384",
      "name": "Total_Payments",
      "redefines": null,
      "baseTypeNamespaceType": null,
      "valueType": "Double"
    },
    {
      "id": "7220000398786709154",
      "name": "Outstanding_Balance",
      "redefines": null,
      "baseTypeNamespaceType": null,
      "valueType": "Double"
    },
    {
      "id": "7220000352510717001",
      "name": "Total_Scholarships",
      "redefines": null,
      "baseTypeNamespaceType": null,
      "valueType": "Double"
    },
    {
      "id": "7220000305772928048",
      "name": "Transaction_Count",
      "redefines": null,
      "baseTypeNamespaceType": null,
      "valueType": "BigInt"
    },
    {
      "id": "7220000263969596407",
      "name": "Average_Tuition",
      "redefines": null,
      "baseTypeNamespaceType": null,
      "valueType": "Double"
    },
    {
      "id": "7220000214104594977",
      "name": "Overdue_Amount",
      "redefines": null,
      "baseTypeNamespaceType": null,
      "valueType": "Double"
    },
    {
      "id": "7220000171182009499",
      "name": "Collection_Rate",
      "redefines": null,
      "baseTypeNamespaceType": null,
      "valueType": "Double"
    },
    {
      "id": "7220000125502206183",
      "name": "Students_with_Overdue_Balance",
      "redefines": null,
      "baseTypeNamespaceType": null,
      "valueType": "BigInt"
    },
    {
      "id": "7220000084628383082",
      "name": "Revenue_Per_Student",
      "redefines": null,
      "baseTypeNamespaceType": null,
      "valueType": "Double"
    },
    {
      "id": "7220000036341066209",
      "name": "MCs_Per_Student",
      "redefines": null,
      "baseTypeNamespaceType": null,
      "valueType": "Double"
    },
    {
      "id": "7219999988657165047",
      "name": "GPA_Per_Student",
      "redefines": null,
      "baseTypeNamespaceType": null,
      "valueType": "Double"
    },
    {
      "id": "7219999943467984813",
      "name": "Avg_Exams_Per_Student",
      "redefines": null,
      "baseTypeNamespaceType": null,
      "valueType": "Double"
    },
    {
      "id": "7219999898580877036",
      "name": "Avg_Courses_Per_Student",
      "redefines": null,
      "baseTypeNamespaceType": null,
      "valueType": "Double"
    },
    {
      "id": "7219999853771298938",
      "name": "Payment_Rate",
      "redefines": null,
      "baseTypeNamespaceType": null,
      "valueType": "Double"
    },
    {
      "id": "7219999807535017358",
      "name": "Scholarship_Rate",
      "redefines": null,
      "baseTypeNamespaceType": null,
      "valueType": "Double"
    }
  ],
  "timeseriesProperties": []
}