[
  {
    "uniqueIdentifier": "9a5d4417-7f5f-4aaf-8f9c-78221133eb63",
    "payload": {
      "name": "Student",
      "description": "Container Description",
      "type": "digitalTwinBuilder"
    },
    "type": "container-v1"
  },
  {
    "uniqueIdentifier": "eaffd9d2-88c5-40d9-8f5c-7a84b08b6bb5",
    "payload": {
      "name": "Student event",
      "runSettings": {
        "executionIntervalInSeconds": 300
      },
      "query": {
        "queryString": "{\"entitySelector\":{\"query\":\"MATCH (node_Student:`Student`) RETURN node_Student.student_key AS `student_key`, node_Student.student_id AS `student_id`, node_Student.first_name AS `first_name`, node_Student.last_name AS `last_name`, node_Student.date_of_birth AS `date_of_birth`, node_Student.gender AS `gender`, node_Student.email AS `email`, node_Student.phone AS `phone`, node_Student.address_street AS `address_street`, node_Student.address_suburb AS `address_suburb`, node_Student.address_state AS `address_state`, node_Student.address_postcode AS `address_postcode`, node_Student.country_of_birth AS `country_of_birth`, node_Student.nationality AS `nationality`, node_Student.domestic_international AS `domestic_international`, node_Student.enrolment_status AS `enrolment_status`, node_Student.enrolment_date AS `enrolment_date`, node_Student.expected_graduation_date AS `expected_graduation_date`, node_Student.program_key AS `program_key`, node_Student.department_key AS `department_key`, node_Student.academic_year_start AS `academic_year_start`, node_Student.scholarship_flag AS `scholarship_flag`, node_Student.scholarship_type AS `scholarship_type`, node_Student.disability_support_flag AS `disability_support_flag`, node_Student.first_in_family_flag AS `first_in_family_flag`, node_Student.permanent_resident_flag AS `permanent_resident_flag`, node_Student.course_key AS `course_key`, node_Student.date_key AS `date_key`\",\"queryType\":\"GQL\"},\"timeSeriesSelector\":{\"entityType\":{\"name\":\"Student\"},\"keyColumns\":{\"student_key\":\"student_key\"},\"metrics\":[{\"field\":\"is_present\"}]}}",
        "compositeKey": {
          "name": "student_key",
          "keys": [
            "student_key"
          ]
        }
      },
      "connection": {
        "itemId": "faabe649-268c-95fb-48df-c2245ec59ec0",
        "workspaceId": "00000000-0000-0000-0000-000000000000",
        "itemType": "DigitalTwinBuilder"
      },
      "eventTimeSettings": {
        "ingestionDelayInSeconds": 0,
        "timeFieldName": "Timestamp"
      },
      "metadata": {
        "digitalTwinBuilderEntityId": "84283902259950"
      },
      "parentContainer": {
        "targetUniqueIdentifier": "9a5d4417-7f5f-4aaf-8f9c-78221133eb63"
      }
    },
    "type": "digitalTwinBuilderSource-v1"
  },
  {
    "uniqueIdentifier": "a2a0e7f4-86a6-45d8-a81c-258e8ddec666",
    "payload": {
      "name": "Student event",
      "parentContainer": {
        "targetUniqueIdentifier": "9a5d4417-7f5f-4aaf-8f9c-78221133eb63"
      },
      "definition": {
        "type": "Event",
        "instance": "{\"steps\":[{\"id\":\"1862ab4e-84fa-40fa-8abb-f166285f3238\",\"name\":\"SourceEventStep\",\"rows\":[{\"arguments\":[{\"name\":\"entityId\",\"type\":\"string\",\"value\":\"eaffd9d2-88c5-40d9-8f5c-7a84b08b6bb5\"}],\"kind\":\"SourceReference\",\"name\":\"SourceSelector\"}]}],\"templateId\":\"SourceEvent\",\"templateVersion\":\"1.2.4\"}"
      }
    },
    "type": "timeSeriesView-v1"
  },
  {
    "uniqueIdentifier": "b35b70e3-e791-43ef-8f56-6889a5bad143",
    "payload": {
      "name": "student_key",
      "parentContainer": {
        "targetUniqueIdentifier": "9a5d4417-7f5f-4aaf-8f9c-78221133eb63"
      },
      "definition": {
        "type": "Object"
      }
    },
    "type": "timeSeriesView-v1"
  },
  {
    "uniqueIdentifier": "218cf526-6dba-4076-ba60-4698427f76c4",
    "payload": {
      "name": "student_key",
      "parentObject": {
        "targetUniqueIdentifier": "b35b70e3-e791-43ef-8f56-6889a5bad143"
      },
      "parentContainer": {
        "targetUniqueIdentifier": "9a5d4417-7f5f-4aaf-8f9c-78221133eb63"
      },
      "definition": {
        "type": "Attribute",
        "instance": "{\"steps\":[{\"id\":\"1d3161e6-9e1e-4be2-a305-0a6a78e97779\",\"name\":\"IdPartStep\",\"rows\":[{\"arguments\":[{\"name\":\"op\",\"type\":\"string\",\"value\":\"Text\"},{\"name\":\"format\",\"type\":\"string\",\"value\":\"\"}],\"kind\":\"TypeAssertion\",\"name\":\"TypeAssertion\"}]}],\"templateId\":\"IdentityPartAttribute\",\"templateVersion\":\"1.2.4\"}"
      }
    },
    "type": "timeSeriesView-v1"
  },
  {
    "uniqueIdentifier": "6e9d68a9-50a5-4bf5-9862-99aa40d2fa29",
    "payload": {
      "name": "student_key",
      "parentObject": {
        "targetUniqueIdentifier": "b35b70e3-e791-43ef-8f56-6889a5bad143"
      },
      "parentContainer": {
        "targetUniqueIdentifier": "9a5d4417-7f5f-4aaf-8f9c-78221133eb63"
      },
      "definition": {
        "type": "Attribute",
        "instance": "{\"steps\":[{\"id\":\"f5bd7e02-4997-4dc1-9a46-8a8aa1d922af\",\"name\":\"IdStructureStep\",\"rows\":[{\"arguments\":[{\"arguments\":[{\"name\":\"entityId\",\"type\":\"string\",\"value\":\"218cf526-6dba-4076-ba60-4698427f76c4\"}],\"kind\":\"AttributeReference\",\"name\":\"idPart\",\"type\":\"complex\"}],\"kind\":\"IdPart\",\"name\":\"IdPart\"}]}],\"templateId\":\"IdentityTupleAttribute\",\"templateVersion\":\"1.2.4\"}"
      }
    },
    "type": "timeSeriesView-v1"
  },
  {
    "uniqueIdentifier": "e0ba27a1-c4de-43ab-9a91-8ea254d7e9a9",
    "payload": {
      "name": "Student event",
      "parentObject": {
        "targetUniqueIdentifier": "b35b70e3-e791-43ef-8f56-6889a5bad143"
      },
      "parentContainer": {
        "targetUniqueIdentifier": "9a5d4417-7f5f-4aaf-8f9c-78221133eb63"
      },
      "definition": {
        "type": "Event",
        "instance": "{\"steps\":[{\"id\":\"fe3bb12f-4646-44db-bd0d-c0814f2927ab\",\"name\":\"SplitEventStep\",\"rows\":[{\"arguments\":[{\"arguments\":[{\"name\":\"entityId\",\"type\":\"string\",\"value\":\"a2a0e7f4-86a6-45d8-a81c-258e8ddec666\"}],\"kind\":\"EventReference\",\"name\":\"event\",\"type\":\"complex\"}],\"kind\":\"Event\",\"name\":\"EventSelector\"},{\"arguments\":[{\"name\":\"fieldName\",\"type\":\"string\",\"value\":\"student_key\"},{\"arguments\":[{\"name\":\"entityId\",\"type\":\"string\",\"value\":\"218cf526-6dba-4076-ba60-4698427f76c4\"}],\"kind\":\"AttributeReference\",\"name\":\"idPart\",\"type\":\"complex\"}],\"kind\":\"FieldIdMapping\",\"name\":\"FieldIdMapping\"},{\"arguments\":[{\"name\":\"isAuthoritative\",\"type\":\"boolean\",\"value\":true}],\"kind\":\"EventOptions\",\"name\":\"SplitEventOptions\"}]}],\"templateId\":\"SplitEvent\",\"templateVersion\":\"1.2.4\"}"
      }
    },
    "type": "timeSeriesView-v1"
  },
  {
    "uniqueIdentifier": "54c02849-f45b-445b-8878-4a9e44434bd7",
    "payload": {
      "name": "is_present",
      "parentObject": {
        "targetUniqueIdentifier": "b35b70e3-e791-43ef-8f56-6889a5bad143"
      },
      "parentContainer": {
        "targetUniqueIdentifier": "9a5d4417-7f5f-4aaf-8f9c-78221133eb63"
      },
      "definition": {
        "type": "Attribute",
        "instance": "{\"steps\":[{\"id\":\"f7e4a422-0248-4b03-ad84-6f7ae56d6503\",\"name\":\"EventSelectStep\",\"rows\":[{\"arguments\":[{\"arguments\":[{\"name\":\"entityId\",\"type\":\"string\",\"value\":\"e0ba27a1-c4de-43ab-9a91-8ea254d7e9a9\"}],\"kind\":\"EventReference\",\"name\":\"event\",\"type\":\"complex\"}],\"kind\":\"Event\",\"name\":\"EventSelector\"},{\"arguments\":[{\"name\":\"fieldName\",\"type\":\"string\",\"value\":\"is_present\"}],\"kind\":\"EventField\",\"name\":\"EventFieldSelector\"}]},{\"id\":\"62252b39-fd90-45aa-bead-be39885674f9\",\"name\":\"EventComputeStep\",\"rows\":[{\"arguments\":[{\"name\":\"op\",\"type\":\"string\",\"value\":\"Text\"},{\"name\":\"format\",\"type\":\"string\",\"value\":\"\"}],\"kind\":\"TypeAssertion\",\"name\":\"TypeAssertion\"}]}],\"templateId\":\"BasicEventAttribute\",\"templateVersion\":\"1.2.4\"}"
      }
    },
    "type": "timeSeriesView-v1"
  },
  {
    "uniqueIdentifier": "695dfe8e-0371-48bc-a28e-8bc18bee4e33",
    "payload": {
      "name": "student_key",
      "parentObject": {
        "targetUniqueIdentifier": "b35b70e3-e791-43ef-8f56-6889a5bad143"
      },
      "parentContainer": {
        "targetUniqueIdentifier": "9a5d4417-7f5f-4aaf-8f9c-78221133eb63"
      },
      "definition": {
        "type": "Attribute",
        "instance": "{\"steps\":[{\"id\":\"10b86dcd-7b91-43ca-b397-766c21bf3107\",\"name\":\"EventSelectStep\",\"rows\":[{\"arguments\":[{\"arguments\":[{\"name\":\"entityId\",\"type\":\"string\",\"value\":\"e0ba27a1-c4de-43ab-9a91-8ea254d7e9a9\"}],\"kind\":\"EventReference\",\"name\":\"event\",\"type\":\"complex\"}],\"kind\":\"Event\",\"name\":\"EventSelector\"},{\"arguments\":[{\"name\":\"fieldName\",\"type\":\"string\",\"value\":\"student_key\"}],\"kind\":\"EventField\",\"name\":\"EventFieldSelector\"}]},{\"id\":\"181699e3-36c1-474d-9732-2ab13107297d\",\"name\":\"EventComputeStep\",\"rows\":[{\"arguments\":[{\"name\":\"op\",\"type\":\"string\",\"value\":\"Text\"},{\"name\":\"format\",\"type\":\"string\",\"value\":\"\"}],\"kind\":\"TypeAssertion\",\"name\":\"TypeAssertion\"}]}],\"templateId\":\"BasicEventAttribute\",\"templateVersion\":\"1.2.4\"}"
      }
    },
    "type": "timeSeriesView-v1"
  },
  {
    "uniqueIdentifier": "1e364a6a-c2dc-4415-ba61-f67b3c0ecdad",
    "payload": {
      "name": "course_key",
      "parentObject": {
        "targetUniqueIdentifier": "b35b70e3-e791-43ef-8f56-6889a5bad143"
      },
      "parentContainer": {
        "targetUniqueIdentifier": "9a5d4417-7f5f-4aaf-8f9c-78221133eb63"
      },
      "definition": {
        "type": "Attribute",
        "instance": "{\"steps\":[{\"id\":\"289e76b2-9168-482c-9ca6-53c614684f55\",\"name\":\"EventSelectStep\",\"rows\":[{\"arguments\":[{\"arguments\":[{\"name\":\"entityId\",\"type\":\"string\",\"value\":\"e0ba27a1-c4de-43ab-9a91-8ea254d7e9a9\"}],\"kind\":\"EventReference\",\"name\":\"event\",\"type\":\"complex\"}],\"kind\":\"Event\",\"name\":\"EventSelector\"},{\"arguments\":[{\"name\":\"fieldName\",\"type\":\"string\",\"value\":\"course_key\"}],\"kind\":\"EventField\",\"name\":\"EventFieldSelector\"}]},{\"id\":\"4eccec43-5410-4e24-816f-9d91901e73b9\",\"name\":\"EventComputeStep\",\"rows\":[{\"arguments\":[{\"name\":\"op\",\"type\":\"string\",\"value\":\"Text\"},{\"name\":\"format\",\"type\":\"string\",\"value\":\"\"}],\"kind\":\"TypeAssertion\",\"name\":\"TypeAssertion\"}]}],\"templateId\":\"BasicEventAttribute\",\"templateVersion\":\"1.2.4\"}"
      }
    },
    "type": "timeSeriesView-v1"
  },
  {
    "uniqueIdentifier": "4b5db039-8e6c-496a-a252-8ee8204f35b6",
    "payload": {
      "name": "date_key",
      "parentObject": {
        "targetUniqueIdentifier": "b35b70e3-e791-43ef-8f56-6889a5bad143"
      },
      "parentContainer": {
        "targetUniqueIdentifier": "9a5d4417-7f5f-4aaf-8f9c-78221133eb63"
      },
      "definition": {
        "type": "Attribute",
        "instance": "{\"steps\":[{\"id\":\"05598bc5-2ce7-4c94-ba90-6af09b3a3703\",\"name\":\"EventSelectStep\",\"rows\":[{\"arguments\":[{\"arguments\":[{\"name\":\"entityId\",\"type\":\"string\",\"value\":\"e0ba27a1-c4de-43ab-9a91-8ea254d7e9a9\"}],\"kind\":\"EventReference\",\"name\":\"event\",\"type\":\"complex\"}],\"kind\":\"Event\",\"name\":\"EventSelector\"},{\"arguments\":[{\"name\":\"fieldName\",\"type\":\"string\",\"value\":\"date_key\"}],\"kind\":\"EventField\",\"name\":\"EventFieldSelector\"}]},{\"id\":\"08d16a8a-9038-406f-8920-6556ed0a5408\",\"name\":\"EventComputeStep\",\"rows\":[{\"arguments\":[{\"name\":\"op\",\"type\":\"string\",\"value\":\"Text\"},{\"name\":\"format\",\"type\":\"string\",\"value\":\"\"}],\"kind\":\"TypeAssertion\",\"name\":\"TypeAssertion\"}]}],\"templateId\":\"BasicEventAttribute\",\"templateVersion\":\"1.2.4\"}"
      }
    },
    "type": "timeSeriesView-v1"
  },
  {
    "uniqueIdentifier": "9b35e31a-1e31-4b15-89b2-d61df101227d",
    "payload": {
      "name": "is_present",
      "parentObject": {
        "targetUniqueIdentifier": "b35b70e3-e791-43ef-8f56-6889a5bad143"
      },
      "parentContainer": {
        "targetUniqueIdentifier": "9a5d4417-7f5f-4aaf-8f9c-78221133eb63"
      },
      "definition": {
        "type": "Attribute",
        "instance": "{\"steps\":[{\"id\":\"1c13f418-f9d5-4525-8e3b-dceebb1a3682\",\"name\":\"EventSelectStep\",\"rows\":[{\"arguments\":[{\"arguments\":[{\"name\":\"entityId\",\"type\":\"string\",\"value\":\"e0ba27a1-c4de-43ab-9a91-8ea254d7e9a9\"}],\"kind\":\"EventReference\",\"name\":\"event\",\"type\":\"complex\"}],\"kind\":\"Event\",\"name\":\"EventSelector\"},{\"arguments\":[{\"name\":\"fieldName\",\"type\":\"string\",\"value\":\"is_present\"}],\"kind\":\"EventField\",\"name\":\"EventFieldSelector\"}]},{\"id\":\"2233b215-d00c-46d3-97d2-4c5f2ee3a6f0\",\"name\":\"EventComputeStep\",\"rows\":[{\"arguments\":[{\"name\":\"op\",\"type\":\"string\",\"value\":\"Text\"},{\"name\":\"format\",\"type\":\"string\",\"value\":\"\"}],\"kind\":\"TypeAssertion\",\"name\":\"TypeAssertion\"}]}],\"templateId\":\"BasicEventAttribute\",\"templateVersion\":\"1.2.4\"}"
      }
    },
    "type": "timeSeriesView-v1"
  },
  {
    "uniqueIdentifier": "a92b5aed-487e-4eeb-a668-fce086313d33",
    "payload": {
      "name": "if student is absent for a course",
      "parentObject": {
        "targetUniqueIdentifier": "b35b70e3-e791-43ef-8f56-6889a5bad143"
      },
      "parentContainer": {
        "targetUniqueIdentifier": "9a5d4417-7f5f-4aaf-8f9c-78221133eb63"
      },
      "definition": {
        "type": "Rule",
        "instance": "{\"templateId\":\"AttributeTrigger\",\"templateVersion\":\"1.2.4\",\"steps\":[{\"name\":\"ScalarSelectStep\",\"id\":\"7c9eae57-0903-4448-bda4-230bf00e5498\",\"rows\":[{\"name\":\"AttributeSelector\",\"kind\":\"Attribute\",\"arguments\":[{\"kind\":\"AttributeReference\",\"type\":\"complex\",\"arguments\":[{\"name\":\"entityId\",\"type\":\"string\",\"value\":\"54c02849-f45b-445b-8878-4a9e44434bd7\"}],\"name\":\"attribute\"}]}]},{\"name\":\"ScalarDetectStep\",\"id\":\"4836b507-a8ed-4f8f-91ac-b7408aa4c8b7\",\"rows\":[{\"name\":\"AnyValueChange\",\"kind\":\"AnyValueChange\",\"arguments\":[{\"name\":\"op\",\"type\":\"string\",\"value\":\"Changes\"}]},{\"name\":\"OccurrenceOption\",\"kind\":\"EachTime\",\"arguments\":[]}]},{\"name\":\"ActStep\",\"id\":\"d9e5e6e1-fe1f-4f5c-bd06-6b6f3e1e122d\",\"rows\":[{\"name\":\"TeamsBinding\",\"kind\":\"TeamsMessage\",\"arguments\":[{\"name\":\"messageLocale\",\"type\":\"string\",\"value\":\"en-us\"},{\"name\":\"recipients\",\"type\":\"array\",\"values\":[{\"type\":\"string\",\"value\":\"admin@MngEnvMCAP906235.onmicrosoft.com\"}]},{\"name\":\"headline\",\"type\":\"array\",\"values\":[{\"type\":\"string\",\"value\":\"Activator alert\"}]},{\"name\":\"optionalMessage\",\"type\":\"array\",\"values\":[{\"type\":\"string\",\"value\":\"The condition has been met\"}]},{\"name\":\"additionalInformation\",\"type\":\"array\",\"values\":[{\"kind\":\"NameReferencePair\",\"type\":\"complex\",\"arguments\":[{\"name\":\"name\",\"type\":\"string\",\"value\":\"student_key\"},{\"kind\":\"AttributeReference\",\"type\":\"complexReference\",\"arguments\":[{\"name\":\"entityId\",\"type\":\"string\",\"value\":\"695dfe8e-0371-48bc-a28e-8bc18bee4e33\"}],\"name\":\"reference\"}]},{\"kind\":\"NameReferencePair\",\"type\":\"complex\",\"arguments\":[{\"name\":\"name\",\"type\":\"string\",\"value\":\"course_key\"},{\"kind\":\"AttributeReference\",\"type\":\"complexReference\",\"arguments\":[{\"name\":\"entityId\",\"type\":\"string\",\"value\":\"1e364a6a-c2dc-4415-ba61-f67b3c0ecdad\"}],\"name\":\"reference\"}]},{\"kind\":\"NameReferencePair\",\"type\":\"complex\",\"arguments\":[{\"name\":\"name\",\"type\":\"string\",\"value\":\"date_key\"},{\"kind\":\"AttributeReference\",\"type\":\"complexReference\",\"arguments\":[{\"name\":\"entityId\",\"type\":\"string\",\"value\":\"4b5db039-8e6c-496a-a252-8ee8204f35b6\"}],\"name\":\"reference\"}]},{\"kind\":\"NameReferencePair\",\"type\":\"complex\",\"arguments\":[{\"name\":\"name\",\"type\":\"string\",\"value\":\"is_present\"},{\"kind\":\"AttributeReference\",\"type\":\"complexReference\",\"arguments\":[{\"name\":\"entityId\",\"type\":\"string\",\"value\":\"9b35e31a-1e31-4b15-89b2-d61df101227d\"}],\"name\":\"reference\"}]}]}]}]}]}",
        "settings": {
          "shouldRun": true,
          "shouldApplyRuleOnUpdate": false
        }
      }
    },
    "type": "timeSeriesView-v1"
  }
]